{
  "code": "EM110",
  "department": "EM",
  "bird_score": 7.82,
  "specific_mentions": 4,
  "is_online_available": true,
  "difficulty_level": {
    "easy_mentions": 2,
    "hard_mentions": 0,
    "workload": 2
  },
  "course_structure": {
    "has_finals": false,
    "has_midterms": false,
    "has_assignments": false,
    "has_projects": false
  },
  "threads": [
    {
      "title": "em110 vs em300",
      "url": "https://www.reddit.com/r/wlu/comments/1hi15bq/em110_vs_em300/",
      "score": 3,
      "created": "2024-12-19T19:39:10.000Z"
    },
    {
      "title": "EM110",
      "url": "https://www.reddit.com/r/wlu/comments/1dih37c/em110/",
      "score": 1,
      "created": "2024-06-18T03:31:45.000Z"
    },
    {
      "title": "EM101 vs EM110 vs EM202/203",
      "url": "https://www.reddit.com/r/wlu/comments/1500qpk/em101_vs_em110_vs_em202203/",
      "score": 0,
      "created": "2023-07-15T03:28:11.000Z"
    },
    {
      "title": "BIRD COURSES",
      "url": "https://www.reddit.com/r/wlu/comments/1fdli6c/bird_courses/",
      "score": 10,
      "created": "2024-09-10T16:03:00.000Z"
    }
  ]
}